mcp_kyvos_sample_client/__init__.py
mcp_kyvos_sample_client/client.py
mcp_kyvos_sample_client/config.py
mcp_kyvos_sample_client/interaction.py
mcp_kyvos_sample_client-1.0.0a1.dist-info/METADATA
mcp_kyvos_sample_client-1.0.0a1.dist-info/WHEEL
mcp_kyvos_sample_client-1.0.0a1.dist-info/entry_points.txt
mcp_kyvos_sample_client-1.0.0a1.dist-info/RECORD
