Metadata-Version: 2.4
Name: mcp-kyvos-sample-client
Version: 1.0.0a1
Summary: A sample client implementation to interact with Kyvos MCP server.
Author-email: Kyvos <support@kyvos.io>
License: MIT License
Requires-Python: >=3.10
Requires-Dist: aiohttp>=3.12.2
Requires-Dist: mcp>=1.9.1
Requires-Dist: openai-agents==0.0.16
Requires-Dist: python-dotenv
Requires-Dist: uv
